evalscope/.DS_Store
evalscope/__init__.py
evalscope/arguments.py
evalscope/config.py
evalscope/constants.py
evalscope/run.py
evalscope/run_arena.py
evalscope/summarizer.py
evalscope/version.py
evalscope/backend/__init__.py
evalscope/backend/base.py
evalscope/backend/opencompass/__init__.py
evalscope/backend/opencompass/api_meta_template.py
evalscope/backend/opencompass/backend_manager.py
evalscope/backend/opencompass/tasks/__init__.py
evalscope/backend/opencompass/tasks/eval_api.py
evalscope/backend/opencompass/tasks/eval_datasets.py
evalscope/backend/rag_eval/__init__.py
evalscope/backend/rag_eval/backend_manager.py
evalscope/backend/rag_eval/clip_benchmark/__init__.py
evalscope/backend/rag_eval/clip_benchmark/arguments.py
evalscope/backend/rag_eval/clip_benchmark/dataset_builder.py
evalscope/backend/rag_eval/clip_benchmark/task_template.py
evalscope/backend/rag_eval/clip_benchmark/tasks/__init__.py
evalscope/backend/rag_eval/clip_benchmark/tasks/image_caption.py
evalscope/backend/rag_eval/clip_benchmark/tasks/zeroshot_classification.py
evalscope/backend/rag_eval/clip_benchmark/tasks/zeroshot_retrieval.py
evalscope/backend/rag_eval/clip_benchmark/utils/webdataset_convert.py
evalscope/backend/rag_eval/clip_benchmark/utils/webdatasets.txt
evalscope/backend/rag_eval/cmteb/__init__.py
evalscope/backend/rag_eval/cmteb/arguments.py
evalscope/backend/rag_eval/cmteb/base.py
evalscope/backend/rag_eval/cmteb/task_template.py
evalscope/backend/rag_eval/cmteb/tasks/Classification.py
evalscope/backend/rag_eval/cmteb/tasks/Clustering.py
evalscope/backend/rag_eval/cmteb/tasks/CustomTask.py
evalscope/backend/rag_eval/cmteb/tasks/PairClassification.py
evalscope/backend/rag_eval/cmteb/tasks/Reranking.py
evalscope/backend/rag_eval/cmteb/tasks/Retrieval.py
evalscope/backend/rag_eval/cmteb/tasks/STS.py
evalscope/backend/rag_eval/cmteb/tasks/__init__.py
evalscope/backend/rag_eval/ragas/__init__.py
evalscope/backend/rag_eval/ragas/arguments.py
unilawbench-1.5.2.dist-info/METADATA
unilawbench-1.5.2.dist-info/WHEEL
unilawbench-1.5.2.dist-info/top_level.txt
unilawbench-1.5.2.dist-info/RECORD
