Metadata-Version: 2.1
Name: unilawbench
Version: 1.5.2
Summary: 中文法律大模型评测工具
Home-page: https://github.com/unilawbench/unilawbench
Author: UniLawBench Team
Author-email: contact@unilawbench.org
Requires-Dist: PyQt5
Requires-Dist: pytrec-eval-terrier
Requires-Dist: accelerate
Requires-Dist: datasets<=3.2.0,>=3.0.0
Requires-Dist: immutabledict
Requires-Dist: jieba
Requires-Dist: jsonlines
Requires-Dist: langdetect
Requires-Dist: latex2sympy2
Requires-Dist: matplotlib
Requires-Dist: modelscope[framework]
Requires-Dist: nltk>=3.9
Requires-Dist: openai
Requires-Dist: pandas
Requires-Dist: pyarrow
Requires-Dist: pyyaml
Requires-Dist: requests
Requires-Dist: rouge-chinese
Requires-Dist: rouge-score>=0.1.0
Requires-Dist: sacrebleu
Requires-Dist: scikit-learn
Requires-Dist: seaborn
Requires-Dist: sympy
Requires-Dist: tabulate
Requires-Dist: torch
Requires-Dist: tqdm
Requires-Dist: transformers>=4.33
Requires-Dist: word2number
Requires-Dist: ms-opencompass>=0.1.4
